fss3wrap/__init__.py
fss3wrap/abstract_fs_class.py
fss3wrap/afs_interface.py
fss3wrap/os_fs_class.py
fss3wrap/s3_fs_class.py
fss3wrap-0.1.21.dist-info/LICENSE.txt
fss3wrap-0.1.21.dist-info/METADATA
fss3wrap-0.1.21.dist-info/WHEEL
fss3wrap-0.1.21.dist-info/top_level.txt
fss3wrap-0.1.21.dist-info/RECORD
