Metadata-Version: 2.1
Name: fss3wrap
Version: 0.1.21
Summary: A python class to wrap fs and fs-s3fs (WIP)
Home-page: https://github.com/carlok/fss3wrap
Author: Carlo Perassi
Author-email: carlo.perassi@kiwifarm.it
License: MIT
Download-URL: https://github.com/carlok/fss3wrap/archive/v_0.1.21.tar.gz
Keywords: fs,s3,wrapper
Platform: UNKNOWN
Classifier: Development Status :: 3 - Alpha
Classifier: Intended Audience :: Developers
Classifier: Topic :: Software Development
Classifier: License :: OSI Approved :: MIT License
Classifier: Programming Language :: Python :: 3
Classifier: Programming Language :: Python :: 3.7
Requires-Dist: fs
Requires-Dist: fs-s3fs-ng
